stadle/__init__.py
stadle/cli.py
stadle/cert/__init__.py
stadle/cert/server.crt
stadle/client/__init__.py
stadle/client/base_admin_agent.py
stadle/client/client.py
stadle/configs/README.md
stadle/configs/config_admin_agent.json
stadle/configs/config_admin_agent_docker.json
stadle/configs/config_agent.json
stadle/lib/__init__.py
stadle/lib/constants/__init__.py
stadle/lib/constants/environment.py
stadle/lib/entity/__init__.py
stadle/lib/entity/model.py
stadle/lib/env/__init__.py
stadle/lib/env/handler.py
stadle/lib/grpc_handler/__init__.py
stadle/lib/grpc_handler/comm.proto
stadle/lib/grpc_handler/comm_pb2.py
stadle/lib/grpc_handler/comm_pb2_grpc.py
stadle/lib/grpc_handler/grpc_client.py
stadle/lib/logging/__init__.py
stadle/lib/logging/log.conf
stadle/lib/logging/logger.py
stadle/lib/util/__init__.py
stadle/lib/util/bm_upload.py
stadle/lib/util/communication_handler.py
stadle/lib/util/exceptions.py
stadle/lib/util/helpers.py
stadle/lib/util/messengers.py
stadle/lib/util/model_conversion.py
stadle/lib/util/states.py
stadle_client-0.8.1.0.dist-info/METADATA
stadle_client-0.8.1.0.dist-info/WHEEL
stadle_client-0.8.1.0.dist-info/entry_points.txt
stadle_client-0.8.1.0.dist-info/top_level.txt
stadle_client-0.8.1.0.dist-info/RECORD
