Metadata-Version: 2.1
Name: stadle-client
Version: 0.8.1.0
Summary: Stadle, A platform for federated learning.
Home-page: https://github.com/tie-set/stadle_dev
Author: Tie-Set Inc
Author-email: package@tie-set.com
License: UNKNOWN
Platform: UNKNOWN
Classifier: Programming Language :: Python :: 3
Classifier: Programming Language :: Python :: 3.8
Requires-Dist: aiohttp<=3.9.5
Requires-Dist: certifi<=2024.7.4
Requires-Dist: click==8.0.3
Requires-Dist: getmac<=0.9.4
Requires-Dist: grpcio-tools==1.64.1
Requires-Dist: grpcio==1.64.1
Requires-Dist: numpy<=1.26.4
Requires-Dist: pyOpenSSL<=24.1.0
Requires-Dist: python-xz<=0.5.0
Requires-Dist: setuptools<=70.3.0
Requires-Dist: typing-extensions<=4.12.2
Requires-Dist: websockets<=11.0.3
Requires-Dist: wheel<=0.43.0
Provides-Extra: dev
Requires-Dist: check-manifest==0.47; extra == "dev"
Requires-Dist: pytest==6.2.5; extra == "dev"
Requires-Dist: tensorflow>=2.5.0; extra == "dev"
Requires-Dist: torch>=2.5.0; extra == "dev"
Requires-Dist: twine==3.7.1; extra == "dev"
